cmaptools/__init__.py
cmaptools/cmaptools.py
cmaptools-0.0.4.dist-info/LICENSE
cmaptools-0.0.4.dist-info/METADATA
cmaptools-0.0.4.dist-info/WHEEL
cmaptools-0.0.4.dist-info/top_level.txt
cmaptools-0.0.4.dist-info/RECORD
